setup.py
ndml_probability_distributions/Binomialdistribution.py
ndml_probability_distributions/Gaussiandistribution.py
ndml_probability_distributions/Generaldistribution.py
ndml_probability_distributions/__init__.py
ndml_probability_distributions.egg-info/PKG-INFO
ndml_probability_distributions.egg-info/SOURCES.txt
ndml_probability_distributions.egg-info/dependency_links.txt
ndml_probability_distributions.egg-info/not-zip-safe
ndml_probability_distributions.egg-info/top_level.txt