Metadata-Version: 1.0
Name: ndml-probability-distributions
Version: 0.1
Summary: Gaussian and Binomial distributions
Home-page: UNKNOWN
Author: Vortana Say
Author-email: sayvortana.itc@gmail.com
License: UNKNOWN
Platform: UNKNOWN
